pyshadow/__init__.py
pyshadow/main.py
pyshadow/resources/querySelector.js
pyshadow/resources/test/button.html
pyshadow/resources/test/index.html
pyshadow/resources/test/script.js
pyshadow/resources/test/style.css
pyshadow-0.0.5.dist-info/LICENSE
pyshadow-0.0.5.dist-info/METADATA
pyshadow-0.0.5.dist-info/WHEEL
pyshadow-0.0.5.dist-info/top_level.txt
pyshadow-0.0.5.dist-info/RECORD
