Metadata-Version: 2.1
Name: pyshadow
Version: 0.0.5
Summary: Selenium plugin to manage shadow DOM elements on web page.
Home-page: https://github.com/sukgu/pyshadow/
Author: Sushil Gupta
Author-email: sushil106768@gmail.com
License: Apache License 2
Classifier: Development Status :: 4 - Beta
Classifier: Intended Audience :: Developers
Classifier: License :: OSI Approved :: Apache Software License
Classifier: Operating System :: OS Independent
Classifier: Topic :: Software Development
Classifier: Topic :: Software Development :: Libraries :: Python Modules
Classifier: Topic :: Software Development :: Quality Assurance
Classifier: Topic :: Software Development :: Testing
Classifier: Topic :: Utilities
Classifier: Programming Language :: Python :: 3.7
Classifier: Programming Language :: Python :: 3.8
Requires-Python: >=3.7
License-File: LICENSE
